payroll/__init__.py
payroll/admin.py
payroll/apps.py
payroll/forms.py
payroll/models.py
payroll/tests.py
payroll/urls.py
payroll/views.py
payroll/migrations/0001_initial.py
payroll/migrations/0002_salary_is_confirm_alter_salary_is_lock.py
payroll/migrations/__init__.py
payroll/migrations/__pycache__/0001_initial.cpython-310.pyc
payroll/migrations/__pycache__/0001_initial.cpython-39.pyc
payroll/migrations/__pycache__/0002_salary_is_confirm_alter_salary_is_lock.cpython-310.pyc
payroll/migrations/__pycache__/0002_salary_is_confirm_alter_salary_is_lock.cpython-39.pyc
payroll/migrations/__pycache__/__init__.cpython-310.pyc
payroll/migrations/__pycache__/__init__.cpython-39.pyc
payroll/templates/payroll/cat_list.html
payroll/templates/payroll/dash.html
payroll/templates/payroll/form.html
payroll/templates/payroll/list.html
payroll/templates/payroll/pos_list.html
payroll/views/__init__.py
payroll/views/payroll_m.py
payroll/views/payroll_v.py
payroll/views/__pycache__/__init__.cpython-310.pyc
payroll/views/__pycache__/__init__.cpython-39.pyc
payroll/views/__pycache__/payroll_m.cpython-310.pyc
payroll/views/__pycache__/payroll_m.cpython-39.pyc
payroll/views/__pycache__/payroll_v.cpython-310.pyc
payroll/views/__pycache__/payroll_v.cpython-39.pyc
django_ipghrms_payroll-1.0.dist-info/LICENSE
django_ipghrms_payroll-1.0.dist-info/METADATA
django_ipghrms_payroll-1.0.dist-info/WHEEL
django_ipghrms_payroll-1.0.dist-info/top_level.txt
django_ipghrms_payroll-1.0.dist-info/RECORD
