Metadata-Version: 2.1
Name: django-ipghrms-payroll
Version: 1.0
Summary: Django IPG HRMS APP PAYROLL
Home-page: http://ipg.tl/
Author: Kinos
Author-email: info@kinos.tl
Maintainer: kinos
Maintainer-email: info@kinos.tl
License: MIT
Classifier: Environment :: Web Environment
Classifier: Framework :: Django
Classifier: Programming Language :: Python :: 3
Classifier: Programming Language :: Python :: 3.7
License-File: LICENSE
